kerground.py
kerground-0.1.1.dist-info/LICENSE
kerground-0.1.1.dist-info/METADATA
kerground-0.1.1.dist-info/WHEEL
kerground-0.1.1.dist-info/top_level.txt
kerground-0.1.1.dist-info/RECORD
