Metadata-Version: 2.1
Name: kerground
Version: 0.1.1
Summary: Stupid simple background worker based on python.
Home-page: https://github.com/ClimenteA/kerground
Author: Climente Alin
Author-email: climente.alin@gmail.com
License: MIT
License-File: LICENSE
